bybit_history/__init__.py
bybit_history/bybit_data_downloader.py
increment_version/__init__.py
increment_version/increment.py
bybit_history-0.1.3.dist-info/LICENSE
bybit_history-0.1.3.dist-info/METADATA
bybit_history-0.1.3.dist-info/WHEEL
bybit_history-0.1.3.dist-info/entry_points.txt
bybit_history-0.1.3.dist-info/RECORD
