Metadata-Version: 2.3
Name: bybit-history
Version: 0.1.3
Summary: A tool to download historical trading data from Bybit public API.
Author: Eugen Soloviov
Author-email: suenot@gmail.com
Requires-Python: >=3.8,<4.0
Classifier: Programming Language :: Python :: 3
Classifier: Programming Language :: Python :: 3.8
Classifier: Programming Language :: Python :: 3.9
Classifier: Programming Language :: Python :: 3.10
Classifier: Programming Language :: Python :: 3.11
Classifier: Programming Language :: Python :: 3.12
Classifier: Programming Language :: Python :: 3.13
Requires-Dist: beautifulsoup4 (>=4.12.3,<5.0.0)
Requires-Dist: requests (>=2.31.0,<3.0.0)
